Metadata-Version: 1.1
Name: logviewer
Version: 1.0.4
Summary: Log monitoring in your browser
Home-page: https://github.com/ridha/logviewer
Author: Abdul Kader Maliyakkal
Author-email: akm.mail@gmail.com
License: UNKNOWN
Platform: UNKNOWN
Classifier: Development Status :: 2 - Pre-Alpha
Classifier: Intended Audience :: Developers
Classifier: Natural Language :: English
Classifier: Programming Language :: Python :: 3
Classifier: Programming Language :: Python :: 3.6
